<?xml version="1.0" encoding="utf-8"?><asx:abap xmlns:asx="http://www.sap.com/abapxml">
<asx:values>
<NAMETAB>
<NAMETAB>
<NAME>OLTPSOURCE</NAME>
<KEY>X</KEY>
<TYPE>C</TYPE>
<LENGTH>000030</LENGTH>
<DECIMALS>-1</DECIMALS>
</NAMETAB>
<NAMETAB>
<NAME>OBJVERS</NAME>
<KEY>X</KEY>
<TYPE>C</TYPE>
<LENGTH>000001</LENGTH>
<DECIMALS>-1</DECIMALS>
</NAMETAB>
<NAMETAB>
<NAME>TYPEHC</NAME>
<KEY></KEY>
<TYPE>C</TYPE>
<LENGTH>000004</LENGTH>
<DECIMALS>-1</DECIMALS>
</NAMETAB>
<NAMETAB>
<NAME>DOMANM</NAME>
<KEY></KEY>
<TYPE>C</TYPE>
<LENGTH>000030</LENGTH>
<DECIMALS>-1</DECIMALS>
</NAMETAB>
<NAMETAB>
<NAME>ROLLNM</NAME>
<KEY></KEY>
<TYPE>C</TYPE>
<LENGTH>000030</LENGTH>
<DECIMALS>-1</DECIMALS>
</NAMETAB>
<NAMETAB>
<NAME>FHCATALOG</NAME>
<KEY></KEY>
<TYPE>C</TYPE>
<LENGTH>000030</LENGTH>
<DECIMALS>-1</DECIMALS>
</NAMETAB>
<NAMETAB>
<NAME>HIETABFL</NAME>
<KEY></KEY>
<TYPE>C</TYPE>
<LENGTH>000001</LENGTH>
<DECIMALS>-1</DECIMALS>
</NAMETAB>
<NAMETAB>
<NAME>HIEVERFL</NAME>
<KEY></KEY>
<TYPE>C</TYPE>
<LENGTH>000001</LENGTH>
<DECIMALS>-1</DECIMALS>
</NAMETAB>
<NAMETAB>
<NAME>HIENMTFL</NAME>
<KEY></KEY>
<TYPE>C</TYPE>
<LENGTH>000001</LENGTH>
<DECIMALS>-1</DECIMALS>
</NAMETAB>
<NAMETAB>
<NAME>HIENDTFL</NAME>
<KEY></KEY>
<TYPE>C</TYPE>
<LENGTH>000001</LENGTH>
<DECIMALS>-1</DECIMALS>
</NAMETAB>
<NAMETAB>
<NAME>HIEINTFL</NAME>
<KEY></KEY>
<TYPE>C</TYPE>
<LENGTH>000001</LENGTH>
<DECIMALS>-1</DECIMALS>
</NAMETAB>
<NAMETAB>
<NAME>STRUC_HDR</NAME>
<KEY></KEY>
<TYPE>C</TYPE>
<LENGTH>000030</LENGTH>
<DECIMALS>-1</DECIMALS>
</NAMETAB>
<NAMETAB>
<NAME>STRUC_HDRT</NAME>
<KEY></KEY>
<TYPE>C</TYPE>
<LENGTH>000030</LENGTH>
<DECIMALS>-1</DECIMALS>
</NAMETAB>
<NAMETAB>
<NAME>STRUC_NODE</NAME>
<KEY></KEY>
<TYPE>C</TYPE>
<LENGTH>000030</LENGTH>
<DECIMALS>-1</DECIMALS>
</NAMETAB>
<NAMETAB>
<NAME>STRUC_NODT</NAME>
<KEY></KEY>
<TYPE>C</TYPE>
<LENGTH>000030</LENGTH>
<DECIMALS>-1</DECIMALS>
</NAMETAB>
<NAMETAB>
<NAME>STRUC_INTV</NAME>
<KEY></KEY>
<TYPE>C</TYPE>
<LENGTH>000030</LENGTH>
<DECIMALS>-1</DECIMALS>
</NAMETAB>
</NAMETAB>
</asx:values>
</asx:abap>